ena/__init__.py
ena_va-0.2.dist-info/METADATA
ena_va-0.2.dist-info/RECORD
ena_va-0.2.dist-info/WHEEL
ena_va-0.2.dist-info/top_level.txt
