Metadata-Version: 2.1
Name: ena-va
Version: 0.2
Summary: Ena is an Electronic Neural Assistant designed for use in the terminal or command prompt
Home-page: http://github.com/madamson8/ena
Author: Matthew Adamson, Heber Brau
Author-email: matthewadamson8@gmail.com
License: MIT
Platform: UNKNOWN
Requires-Python: >=3
Requires-Dist: passlib (==1.7.1)
Requires-Dist: psycopg2 (==2.7.4)
